mlux_reactly/__init__.py
mlux_reactly/agent.py
mlux_reactly/core.py
mlux_reactly/framework.py
mlux_reactly/py.typed
mlux_reactly/stages.py
mlux_reactly/types.py
mlux_reactly-0.1.dist-info/METADATA
mlux_reactly-0.1.dist-info/WHEEL
mlux_reactly-0.1.dist-info/top_level.txt
mlux_reactly-0.1.dist-info/RECORD
