Metadata-Version: 2.4
Name: mlux-reactly
Version: 0.1
Summary:  ReAct inspired Agent developed from scratch using Ollama. This agent uses task decomposition and uses provided tools.
Author-email: Donovan <don.k@gmx.at>
Project-URL: Repository, https://github.com/d-volution/mlux-reactly
Requires-Python: >=3.12
Requires-Dist: numexpr>=2.10
Requires-Dist: ollama>=0.5
